scripts/find_best_rank.py
tests/__init__.py
tests/conftest.py
tests/requirements-test.txt
tests/test_batch_inference.py
tests/test_cli.py
tests/test_features.py
tests/test_model_agnostic_cli.py
tests/test_security.py
tests/test_training_pipeline.py
vaultide/__init__.py
vaultide/config.py
vaultide/cli/__init__.py
vaultide/cli/cli.py
vaultide/cli/features.py
vaultide/cli/main.py
vaultide/cli/security.py
vaultide/esm2/__init__.py
vaultide/esm2/batch_inference.py
vaultide/esm2/inference.py
vaultide/esm2/serve.py
vaultide/esm2/training_pipeline.py
vaultide/esmc/__init__.py
vaultide/esmc/batch_inference.py
vaultide/esmc/inference.py
vaultide/esmc/serve.py
vaultide/esmc/training_pipeline.py
vaultide-0.1.0.dist-info/licenses/LICENSE
vaultide-0.1.0.dist-info/METADATA
vaultide-0.1.0.dist-info/WHEEL
vaultide-0.1.0.dist-info/entry_points.txt
vaultide-0.1.0.dist-info/top_level.txt
vaultide-0.1.0.dist-info/RECORD
