Metadata-Version: 2.4
Name: vaultide
Version: 0.1.0
Summary: CLI interface for training biomolecular model LoRAs
Author: Vaultide Team
License: MIT
Classifier: Development Status :: 3 - Alpha
Classifier: Intended Audience :: Science/Research
Classifier: License :: OSI Approved :: MIT License
Classifier: Operating System :: OS Independent
Classifier: Programming Language :: Python :: 3.10
Classifier: Programming Language :: Python :: 3.11
Classifier: Programming Language :: Python :: 3.12
Classifier: Topic :: Scientific/Engineering :: Artificial Intelligence
Classifier: Topic :: Scientific/Engineering :: Bio-Informatics
Requires-Python: >=3.10
License-File: LICENSE
Requires-Dist: torch>=2.0.0
Requires-Dist: transformers>=4.30.0
Requires-Dist: pandas<2.2.0,>=2.1.0
Requires-Dist: scikit-learn>=1.3.0
Requires-Dist: xgboost>=1.7.0
Requires-Dist: peft>=0.4.0
Requires-Dist: torchmetrics>=0.11.0
Requires-Dist: tqdm>=4.65.0
Requires-Dist: pyyaml>=6.0
Requires-Dist: numpy<2.0.0,>=1.25.0
Requires-Dist: pydantic>=2.11.7
Requires-Dist: pandas-stubs>=2.2.2.240807
Requires-Dist: types-tqdm>=4.67.0.20250516
Requires-Dist: fastapi>=0.116.1
Requires-Dist: uvicorn>=0.35.0
Requires-Dist: click>=8.1.8
Requires-Dist: protobuf>=6.31.1
Requires-Dist: esm>=2.0.0
Dynamic: license-file
